terraform_utils/__init__.py
terraform_utils/command_line.py
terraform_utils/core.py
terraform_utils/data/common.tfvars
terraform_utils/data/hello.txt
terraform_utils/data/terragrunt.hcl
terraform_utils/utils/__init__.py
terraform_utils/utils/mockio.py
terraform_utils-0.1.3.dist-info/LICENSE
terraform_utils-0.1.3.dist-info/METADATA
terraform_utils-0.1.3.dist-info/WHEEL
terraform_utils-0.1.3.dist-info/entry_points.txt
terraform_utils-0.1.3.dist-info/top_level.txt
terraform_utils-0.1.3.dist-info/RECORD
