Metadata-Version: 2.1
Name: terraform-utils
Version: 0.1.3
Summary: UNKNOWN
Home-page: https://github.com/rkhullar/terraform-utils
Author: Rajan Khullar
Author-email: rkhullar03@gmail.com
License: MIT
Keywords: terraform terragrunt aws
Platform: UNKNOWN
